dshelpertool/__init__.py
dshelpertool/cleaning.py
dshelpertool/cli.py
dshelpertool/dtypes.py
dshelpertool/easter_egg.py
dshelpertool/eda.py
dshelpertool/overview.py
dshelpertool/report.py
dshelpertool/stats.py
dshelpertool/viz.py
dshelpertool-0.1.0.dist-info/licenses/LICENSE
tests/__init__.py
tests/test_cleaning.py
tests/test_overview.py
dshelpertool-0.1.0.dist-info/METADATA
dshelpertool-0.1.0.dist-info/WHEEL
dshelpertool-0.1.0.dist-info/entry_points.txt
dshelpertool-0.1.0.dist-info/top_level.txt
dshelpertool-0.1.0.dist-info/RECORD
